pycodesnap/__init__.py
pycodesnap/codesnap.py
pycodesnap-0.2.dist-info/METADATA
pycodesnap-0.2.dist-info/WHEEL
pycodesnap-0.2.dist-info/top_level.txt
pycodesnap-0.2.dist-info/RECORD
