Metadata-Version: 2.4
Name: pycodesnap
Version: 0.2
Summary: PyCodeSnap for format codes and code to image.
Home-page: https://github.com/shayanheidari01/pycodesnap
Author: Shayan Heidari
Author-email: contact@shayanheidari.info
Keywords: codesnap,code,image
Classifier: Programming Language :: Python :: 3.7
Classifier: Programming Language :: Python :: 3.8
Classifier: Programming Language :: Python :: 3.9
Classifier: Programming Language :: Python :: 3.10
Classifier: Programming Language :: Python :: 3.11
Classifier: Programming Language :: Python :: 3.12
Classifier: Programming Language :: Python :: 3.13
Classifier: License :: OSI Approved :: MIT License
Requires-Python: ~=3.6
Requires-Dist: pillow
Requires-Dist: pygments
Dynamic: author
Dynamic: author-email
Dynamic: classifier
Dynamic: description
Dynamic: description-content-type
Dynamic: home-page
Dynamic: keywords
Dynamic: requires-dist
Dynamic: requires-python
Dynamic: summary
